HIT_network/__init__.py
HIT_network/draw_networks.py
HIT_network/random_networks.py
HIT_network/read_txt_networks.py
HIT_network/scale_of_network.py
HIT_network-0.0.3.dist-info/METADATA
HIT_network-0.0.3.dist-info/WHEEL
HIT_network-0.0.3.dist-info/top_level.txt
HIT_network-0.0.3.dist-info/RECORD
